wixok/__init__.py
wixok/jsonfile.py
wixok_jsonfile-25.8.3.dist-info/licenses/LICENSE
wixok_jsonfile-25.8.3.dist-info/METADATA
wixok_jsonfile-25.8.3.dist-info/WHEEL
wixok_jsonfile-25.8.3.dist-info/entry_points.txt
wixok_jsonfile-25.8.3.dist-info/top_level.txt
wixok_jsonfile-25.8.3.dist-info/RECORD
