Metadata-Version: 2.4
Name: wixok.jsonfile
Version: 25.8.3
Summary: Simple Python package for text file operations.
Author-email: Wixok <contact@wixok.com>
Maintainer-email: Mohammed Dellihr <mohammeddellihr@maildoo.com>
License: The MIT License (MIT)
Project-URL: Repository, https://github.com/wixok/jsonfile
Project-URL: Issues, https://github.com/wixok/jsonfile/issues
Keywords: text,file,io,toolkit,jsonfile
Classifier: License :: OSI Approved :: MIT License
Classifier: Programming Language :: Python :: 3
Requires-Python: >=3.8
License-File: LICENSE
Provides-Extra: dev
Requires-Dist: pytest; extra == "dev"
Dynamic: license-file
